raster_basics/BaseFunctions.py
raster_basics/DataPlots.py
raster_basics/GlacierFunctions.py
raster_basics/NoiseFunctions.py
raster_basics/RasterBasics.py
raster_basics/SmoothingFunctions.py
raster_basics/__init__.py
raster_basics-1.5.8.dist-info/METADATA
raster_basics-1.5.8.dist-info/WHEEL
raster_basics-1.5.8.dist-info/top_level.txt
raster_basics-1.5.8.dist-info/RECORD
