Metadata-Version: 2.1
Name: raster_basics
Version: 1.5.8
Summary: Basic GeoTIFF Processing
Author-email: Albin Wells <awwells@andrew.cmu.edu>
Project-URL: documentation, https://github.com/albinwwells/Raster-Basics/tree/main
Project-URL: repository, https://github.com/albinwwells/Raster-Basics/tree/main
Classifier: Programming Language :: Python :: 3
Requires-Python: >=3.6
Requires-Dist: earthpy
Requires-Dist: Fiona
Requires-Dist: geopandas
Requires-Dist: ipykernel
Requires-Dist: jupyter
Requires-Dist: matplotlib
Requires-Dist: matplotlib_scalebar
Requires-Dist: numpy
Requires-Dist: pandas
Requires-Dist: pyproj
Requires-Dist: rasterio
Requires-Dist: rioxarray
Requires-Dist: scipy
Requires-Dist: Shapely
Requires-Dist: tqdm
Requires-Dist: xarray
